pysiphon/__init__.py
pysiphon/cli.py
pysiphon/client.py
pysiphon/utils.py
pysiphon/generated/__init__.py
pysiphon/generated/siphon_service_pb2.py
pysiphon/generated/siphon_service_pb2_grpc.py
pysiphon-1.2.0.dist-info/METADATA
pysiphon-1.2.0.dist-info/WHEEL
pysiphon-1.2.0.dist-info/entry_points.txt
pysiphon-1.2.0.dist-info/top_level.txt
pysiphon-1.2.0.dist-info/RECORD
