Metadata-Version: 2.4
Name: pysiphon
Version: 1.2.0
Summary: Python gRPC client for Siphon service - memory manipulation, input control, and screen capture
Requires-Python: >=3.10
Requires-Dist: grpcio>=1.59.0
Requires-Dist: grpcio-tools>=1.59.0
Requires-Dist: tomli>=2.0.1
Requires-Dist: Pillow>=10.0.0
Requires-Dist: click>=8.1.0
